[
  {
    "metricId": "size",
    "type": "areaOverlap",
    "layerId": "IQM2iyEoL",
    "objectiveId": "30percent",
    "classes": [
      {
        "classId": "planningArea",
        "display": "Raet NP",
        "datasourceId": "planningArea"
      }
    ]
  },
  {
    "metricId": "ous",
    "type": "valueOverlap",
    "classes": [
      {
        "classId": "ous_recRodAndLine",
        "display": "Recreational Fishing - Rod and Line",
        "datasourceId": "ous_recRodAndLine",
        "layerId": "D7FID3zQ8"
      },
      {
        "classId": "ous_recPassiveGear",
        "display": "Recreational Fishing - Passive Gear",
        "datasourceId": "ous_recPassiveGear",
        "layerId": "ycyDA8HUP"
      },
      {
        "classId": "ous_comTrawling",
        "display": "Commercial Fishing - Trawling",
        "datasourceId": "ous_comTrawling",
        "layerId": "KnB0RZOtm"
      },
      {
        "classId": "ous_comNonTrawling",
        "display": "Commercial Fishing - Non-Trawling",
        "datasourceId": "ous_comNonTrawling",
        "layerId": "Rs1BBq5yR"
      },
      {
        "classId": "ous_divingHarvesting",
        "display": "Diving - Harvesting",
        "datasourceId": "ous_divingHarvesting",
        "layerId": "xDyxK6Eu1"
      },
      {
        "classId": "ous_divingNonHarvesting",
        "display": "Diving - Non-Harvesting",
        "datasourceId": "ous_divingNonHarvesting",
        "layerId": "llwvBfHdv"
      }
    ]
  },
  {
    "metricId": "depth",
    "type": "valueOverlap",
    "layerId": "t4Zdhro31",
    "datasourceId": "depth",
    "classes": [
      { "classId": "min", "display": "Min" },
      { "classId": "mean", "display": "Mean" },
      { "classId": "max", "display": "Max" }
    ]
  },
  {
    "metricId": "eelgrass",
    "type": "areaOverlap",
    "classes": [
      {
        "classId": "eelgrass",
        "display": "Eelgrass",
        "datasourceId": "eelgrass",
        "layerId": "Zt39cK1uX"
      }
    ]
  },
  {
    "metricId": "kelp",
    "type": "areaOverlap",
    "classes": [
      {
        "classId": "kelp",
        "display": "Kelp Forest",
        "datasourceId": "kelp",
        "layerId": "EYzEmadch"
      }
    ]
  },
  {
    "metricId": "bioclasticSand",
    "type": "areaOverlap",
    "classes": [
      {
        "classId": "bioclasticSand",
        "display": "Bioclastic Sand",
        "datasourceId": "bioclasticSand",
        "layerId": "0pIOvT11X"
      }
    ]
  },
  {
    "metricId": "codSpawningGrounds",
    "type": "areaOverlap",
    "classes": [
      {
        "classId": "codSpawningGrounds",
        "display": "Cod Spawning Grounds",
        "datasourceId": "cod_spawning_grounds",
        "layerId": "Y1qY5FyUq"
      }
    ]
  },
  {
    "metricId": "seabirdNests",
    "type": "countOverlap",
    "classes": [
      {
        "classId": "makrellterne",
        "display": "Common tern",
        "datasourceId": "makrellterne",
        "layerId": "FU03eLGgk"
      },
      {
        "classId": "hettemaake",
        "display": "Black-headed gull",
        "datasourceId": "hettemaake",
        "layerId": "MBQRM2Uh8"
      },
      {
        "classId": "graamaake",
        "display": "European herring gull",
        "datasourceId": "graamaake",
        "layerId": "z94tkKp76"
      },
      {
        "classId": "fiskemaake",
        "display": "Common gull",
        "datasourceId": "fiskemaake",
        "layerId": "yjV3IYySK"
      },
      {
        "classId": "storskarv",
        "display": "Great cormorant",
        "datasourceId": "storskarv",
        "layerId": "WkfRXvwPc"
      },
      {
        "classId": "svartbak",
        "display": "Great black-backed gull",
        "datasourceId": "svartbak",
        "layerId": "sFnSzgyUw"
      },
      {
        "classId": "tjeld",
        "display": "Eurasian oystercatcher",
        "datasourceId": "tjeld",
        "layerId": "ttB24nBJ0"
      },
      {
        "classId": "aerfugl",
        "display": "Common eider",
        "datasourceId": "aerfugl",
        "layerId": "zxdvcGS0q"
      }
    ]
  }
]
